{
  "Type": "Variant",
  "Reference": "Template_Summoned_Ally",
  "Modify": {
    "MaxHealth": 250,
    "HearingRange": 8,
    "ViewSector": 270,
    "Appearance": "Skeleton_Sand_Soldier",
    "Weapons": [
      "Weapon_Spear_Bronze"
    ],
    "DefaultOffHandSlot": 0,
    "FlockArray": [
      "Skeleton_Sand_Soldier"
    ],
    "Attack": "Root_NPC_Skeleton_Sand_Soldier_Attack",
    "AttackDistance": 3,
    "DesiredAttackDistanceRange": [
      2,
      2.5
    ],
    "ApplySeparation": true,
    "NameTranslationKey": "server.npcRoles.Skeleton_Sand_Soldier.name"
  }
}